{
  "area": 13.7632,
  "cell_footprint": "sky130_fd_sc_hd__einvn",
  "cell_leakage_power": 8.806838e-05,
  "driver_waveform_fall": "ramp",
  "driver_waveform_rise": "ramp",
  "leakage_power": [
    {
      "value": 6.2127475e-05,
      "when": "!A&TE_B"
    },
    {
      "value": 4.6855925e-05,
      "when": "!A&!TE_B"
    },
    {
      "value": 5.4571737e-05,
      "when": "A&TE_B"
    },
    {
      "value": 0.0001887,
      "when": "A&!TE_B"
    }
  ],
  "pg_pin,VGND": {
    "pg_type": "primary_ground",
    "related_bias_pin": "VPB",
    "voltage_name": "VGND"
  },
  "pg_pin,VNB": {
    "pg_type": "nwell",
    "physical_connection": "device_layer",
    "voltage_name": "VNB"
  },
  "pg_pin,VPB": {
    "pg_type": "pwell",
    "physical_connection": "device_layer",
    "voltage_name": "VPB"
  },
  "pg_pin,VPWR": {
    "pg_type": "primary_power",
    "related_bias_pin": "VNB",
    "voltage_name": "VPWR"
  },
  "pin,A": {
    "capacitance": 0.007248,
    "clock": "false",
    "direction": "input",
    "fall_capacitance": 0.006915,
    "internal_power": {
      "fall_power,power_inputs_1": {
        "index_1": [
          0.01,
          0.0316228,
          0.1,
          0.316228,
          1.0,
          3.16228,
          9.9999999
        ],
        "values": [
          0.0053275,
          0.0053192,
          0.0052931,
          0.0052928,
          0.0052918,
          0.0052888,
          0.0052791
        ]
      },
      "rise_power,power_inputs_1": {
        "index_1": [
          0.01,
          0.0316228,
          0.1,
          0.316228,
          1.0,
          3.16228,
          9.9999999
        ],
        "values": [
          -0.0047425,
          -0.0047485,
          -0.0047672,
          -0.0047609,
          -0.0047409,
          -0.0046775,
          -0.0044773
        ]
      }
    },
    "max_transition": 10.0,
    "related_ground_pin": "VGND",
    "related_power_pin": "VPWR",
    "rise_capacitance": 0.00758
  },
  "pin,TE_B": {
    "capacitance": 0.005725,
    "clock": "false",
    "direction": "input",
    "fall_capacitance": 0.005186,
    "max_transition": 10.0,
    "related_ground_pin": "VGND",
    "related_power_pin": "VPWR",
    "rise_capacitance": 0.006264
  },
  "pin,Z": {
    "capacitance": 0.003908,
    "direction": "output",
    "function": "(!A)",
    "internal_power": [
      {
        "fall_power,power_outputs_1": {
          "index_1": [
            0.01,
            0.03162278,
            0.1,
            0.3162278,
            1,
            3.162278,
            10
          ],
          "index_2": [
            0.0005,
            0.001473908,
            0.004344808,
            0.01280769,
            0.03775471,
            0.1112939,
            0.3280739
          ],
          "values": [
            [
              0.0010326,
              0.0002034,
              -0.0023408,
              -0.0099571,
              -0.032604,
              -0.0995689,
              -0.2971012
            ],
            [
              0.0008072,
              4.28e-05,
              -0.0023874,
              -0.0099392,
              -0.0325129,
              -0.0994734,
              -0.2969954
            ],
            [
              0.0004418,
              -0.0003003,
              -0.0026104,
              -0.0099638,
              -0.0324308,
              -0.0993327,
              -0.2968387
            ],
            [
              1.8e-05,
              -0.0007445,
              -0.0030645,
              -0.0102747,
              -0.0325545,
              -0.0992992,
              -0.2967549
            ],
            [
              -4.84e-05,
              -0.0008334,
              -0.0032583,
              -0.0107349,
              -0.0329975,
              -0.099517,
              -0.2968115
            ],
            [
              -0.00038,
              -0.0012049,
              -0.0037091,
              -0.0111717,
              -0.0334376,
              -0.1000777,
              -0.297096
            ],
            [
              -0.0007751,
              -0.001659,
              -0.0041841,
              -0.0117127,
              -0.0341794,
              -0.100718,
              -0.2978633
            ]
          ]
        },
        "related_pin": "A",
        "rise_power,power_outputs_1": {
          "index_1": [
            0.01,
            0.03162278,
            0.1,
            0.3162278,
            1,
            3.162278,
            10
          ],
          "index_2": [
            0.0005,
            0.001473908,
            0.004344808,
            0.01280769,
            0.03775471,
            0.1112939,
            0.3280739
          ],
          "values": [
            [
              0.0087739,
              0.0098148,
              0.0126585,
              0.0204692,
              0.0431563,
              0.1093245,
              0.3047837
            ],
            [
              0.0083499,
              0.0093849,
              0.0122994,
              0.0203026,
              0.0431317,
              0.109404,
              0.3053708
            ],
            [
              0.0079311,
              0.008923,
              0.0117532,
              0.0197976,
              0.0427841,
              0.1096547,
              0.3050031
            ],
            [
              0.0076671,
              0.0085986,
              0.0113132,
              0.0191977,
              0.0422586,
              0.1089493,
              0.3050733
            ],
            [
              0.0074694,
              0.0083731,
              0.0110655,
              0.0187821,
              0.0415354,
              0.1085572,
              0.3045482
            ],
            [
              0.0073336,
              0.0082459,
              0.0109311,
              0.0184969,
              0.0409842,
              0.1079534,
              0.3039841
            ],
            [
              0.0066355,
              0.0075114,
              0.0101742,
              0.0177203,
              0.0412108,
              0.1074428,
              0.3030272
            ]
          ]
        }
      },
      {
        "fall_power,power_outputs_1": {
          "index_1": [
            0.01,
            0.03162278,
            0.1,
            0.3162278,
            1,
            3.162278,
            10
          ],
          "index_2": [
            0.0005,
            0.001473908,
            0.004344808,
            0.01280769,
            0.03775471,
            0.1112939,
            0.3280739
          ],
          "values": [
            [
              -0.0061328,
              -0.0060836,
              -0.0059614,
              -0.00575,
              -0.005514,
              -0.0053614,
              -0.0052926
            ],
            [
              -0.006171,
              -0.0061419,
              -0.0060166,
              -0.0058095,
              -0.0055832,
              -0.0054364,
              -0.0053751
            ],
            [
              -0.0062779,
              -0.0062297,
              -0.0061242,
              -0.0059384,
              -0.0057132,
              -0.0055701,
              -0.0055015
            ],
            [
              -0.0065178,
              -0.0064733,
              -0.0063609,
              -0.0061739,
              -0.0059333,
              -0.0057712,
              -0.0056946
            ],
            [
              -0.006838,
              -0.0068009,
              -0.0067056,
              -0.006507,
              -0.0062369,
              -0.0060198,
              -0.0059089
            ],
            [
              -0.0071681,
              -0.0071502,
              -0.0070782,
              -0.00693,
              -0.0066765,
              -0.0063937,
              -0.0061836
            ],
            [
              -0.0073276,
              -0.0073382,
              -0.0072867,
              -0.0071828,
              -0.006967,
              -0.0067055,
              -0.006431
            ]
          ]
        },
        "related_pin": "TE_B",
        "rise_power,power_outputs_1": {
          "index_1": [
            0.01,
            0.03162278,
            0.1,
            0.3162278,
            1,
            3.162278,
            10
          ],
          "index_2": [
            0.0005,
            0.001473908,
            0.004344808,
            0.01280769,
            0.03775471,
            0.1112939,
            0.3280739
          ],
          "values": [
            [
              0.0252266,
              0.0261652,
              0.028814,
              0.036449,
              0.0588761,
              0.1253986,
              0.3208934
            ],
            [
              0.0251809,
              0.0261059,
              0.0287527,
              0.0363717,
              0.0588882,
              0.1251311,
              0.3209764
            ],
            [
              0.0250583,
              0.0259855,
              0.0286077,
              0.0362419,
              0.0586926,
              0.1249773,
              0.3210857
            ],
            [
              0.0249291,
              0.0258622,
              0.0284806,
              0.0361175,
              0.0585586,
              0.1248564,
              0.3205383
            ],
            [
              0.0248471,
              0.0257691,
              0.028411,
              0.0360745,
              0.058572,
              0.1250046,
              0.3214787
            ],
            [
              0.0247005,
              0.0256496,
              0.0283605,
              0.0359266,
              0.0584041,
              0.1247035,
              0.3204441
            ],
            [
              0.0241286,
              0.0250389,
              0.0276196,
              0.0353186,
              0.0583967,
              0.1246167,
              0.3205195
            ]
          ]
        },
        "when": "!A"
      },
      {
        "fall_power,power_outputs_1": {
          "index_1": [
            0.01,
            0.03162278,
            0.1,
            0.3162278,
            1,
            3.162278,
            10
          ],
          "index_2": [
            0.0005,
            0.001473908,
            0.004344808,
            0.01280769,
            0.03775471,
            0.1112939,
            0.3280739
          ],
          "values": [
            [
              0.0206245,
              0.0198171,
              0.0174289,
              0.0100694,
              -0.0125065,
              -0.0794904,
              -0.2769843
            ],
            [
              0.0205644,
              0.0197562,
              0.0173809,
              0.0100119,
              -0.0125592,
              -0.0795499,
              -0.2770865
            ],
            [
              0.0204333,
              0.0196212,
              0.0172392,
              0.0098824,
              -0.0126876,
              -0.079678,
              -0.2772163
            ],
            [
              0.0203081,
              0.0195203,
              0.0171291,
              0.0097556,
              -0.0128141,
              -0.0797908,
              -0.2773269
            ],
            [
              0.0202097,
              0.0194221,
              0.0170306,
              0.0096556,
              -0.0129175,
              -0.0798986,
              -0.2773765
            ],
            [
              0.0192926,
              0.0185762,
              0.0163546,
              0.0094233,
              -0.0129689,
              -0.0799486,
              -0.2774851
            ],
            [
              0.0202304,
              0.0193386,
              0.0167263,
              0.0090166,
              -0.0137158,
              -0.0806922,
              -0.2775312
            ]
          ]
        },
        "related_pin": "TE_B",
        "rise_power,power_outputs_1": {
          "index_1": [
            0.01,
            0.03162278,
            0.1,
            0.3162278,
            1,
            3.162278,
            10
          ],
          "index_2": [
            0.0005,
            0.001473908,
            0.004344808,
            0.01280769,
            0.03775471,
            0.1112939,
            0.3280739
          ],
          "values": [
            [
              -0.0065773,
              -0.0065993,
              -0.0066251,
              -0.0066624,
              -0.0066919,
              -0.0067308,
              -0.0067381
            ],
            [
              -0.0066269,
              -0.0066362,
              -0.0066606,
              -0.0066786,
              -0.0067279,
              -0.0067623,
              -0.0067795
            ],
            [
              -0.0067363,
              -0.0067454,
              -0.0067439,
              -0.0067815,
              -0.0068246,
              -0.0068611,
              -0.006865
            ],
            [
              -0.0069156,
              -0.0069342,
              -0.0069309,
              -0.0069681,
              -0.0070085,
              -0.0070372,
              -0.0070518
            ],
            [
              -0.0071432,
              -0.0071514,
              -0.0071709,
              -0.007196,
              -0.0072304,
              -0.0072543,
              -0.0072663
            ],
            [
              -0.0073518,
              -0.0073601,
              -0.0073841,
              -0.0074124,
              -0.0074445,
              -0.0074537,
              -0.007463
            ],
            [
              -0.0074995,
              -0.0075053,
              -0.0075195,
              -0.0075368,
              -0.007565,
              -0.0075886,
              -0.0075923
            ]
          ]
        },
        "when": "A"
      }
    ],
    "max_capacitance": 0.328074,
    "max_transition": 10.001101,
    "power_down_function": "(!VPWR + VGND)",
    "related_ground_pin": "VGND",
    "related_power_pin": "VPWR",
    "three_state": "(TE_B)",
    "timing": [
      {
        "cell_fall,del_1_7_7": {
          "index_1": [
            0.01,
            0.0316228,
            0.1,
            0.316228,
            1,
            3.16228,
            10
          ],
          "index_2": [
            0.0044084,
            0.00538231,
            0.00825321,
            0.0167161,
            0.0416631,
            0.115202,
            0.331982
          ],
          "values": [
            [
              0.0389054,
              0.0428356,
              0.0541336,
              0.086862,
              0.1837973,
              0.4715658,
              1.3192183
            ],
            [
              0.0490103,
              0.0533183,
              0.0649928,
              0.0977085,
              0.1946134,
              0.4826743,
              1.3358377
            ],
            [
              0.0848437,
              0.0890757,
              0.1011348,
              0.1347526,
              0.2319494,
              0.5202079,
              1.3679939
            ],
            [
              0.1769418,
              0.1864737,
              0.2070765,
              0.2515989,
              0.3467597,
              0.6363903,
              1.4878958
            ],
            [
              0.3916903,
              0.4106642,
              0.4545094,
              0.5464139,
              0.7078579,
              1.0085501,
              1.8524462
            ],
            [
              0.8880303,
              0.9324592,
              1.0349444,
              1.2339519,
              1.5715264,
              2.1103754,
              3.0305043
            ],
            [
              1.9722664,
              2.0878661,
              2.3585458,
              2.8549136,
              3.6184968,
              4.7423332,
              6.4466428
            ]
          ]
        },
        "cell_rise,del_1_7_7": {
          "index_1": [
            0.01,
            0.0316228,
            0.1,
            0.316228,
            1,
            3.16228,
            10
          ],
          "index_2": [
            0.0044084,
            0.00538231,
            0.00825321,
            0.0167161,
            0.0416631,
            0.115202,
            0.331982
          ],
          "values": [
            [
              0.1877482,
              0.2150673,
              0.2890234,
              0.4936562,
              1.0842885,
              2.8138323,
              7.9063422
            ],
            [
              0.1871622,
              0.2139752,
              0.2897936,
              0.4992863,
              1.0925953,
              2.8237157,
              7.9151166
            ],
            [
              0.2143402,
              0.2400002,
              0.314014,
              0.5240705,
              1.1203402,
              2.8620681,
              7.9461238
            ],
            [
              0.3385078,
              0.3629318,
              0.4338279,
              0.6383915,
              1.2382706,
              2.9668272,
              8.0745393
            ],
            [
              0.7435785,
              0.7771351,
              0.8507354,
              1.050715,
              1.6433477,
              3.3799081,
              8.500554
            ],
            [
              1.8331033,
              1.8958581,
              2.0407678,
              2.3552145,
              2.9657783,
              4.6957696,
              9.7842081
            ],
            [
              4.6973385,
              4.8127071,
              5.1898046,
              5.8349534,
              6.9820163,
              8.9246752,
              13.9955221
            ]
          ]
        },
        "fall_transition,del_1_7_7": {
          "index_1": [
            0.01,
            0.0316228,
            0.1,
            0.316228,
            1,
            3.16228,
            10
          ],
          "index_2": [
            0.0044084,
            0.00538231,
            0.00825321,
            0.0167161,
            0.0416631,
            0.115202,
            0.331982
          ],
          "values": [
            [
              0.0212886,
              0.0260785,
              0.0406536,
              0.0835881,
              0.2110789,
              0.5854335,
              1.6879315
            ],
            [
              0.0212348,
              0.0262655,
              0.0405198,
              0.0836287,
              0.2101417,
              0.5849229,
              1.6754709
            ],
            [
              0.0231197,
              0.027261,
              0.040736,
              0.0833087,
              0.210013,
              0.5864098,
              1.6878839
            ],
            [
              0.0476908,
              0.052059,
              0.0659555,
              0.0972233,
              0.2116484,
              0.5865843,
              1.6760251
            ],
            [
              0.1127444,
              0.1228067,
              0.1470184,
              0.1944719,
              0.2939855,
              0.5967788,
              1.6807462
            ],
            [
              0.3013141,
              0.322447,
              0.3704665,
              0.4578043,
              0.6085193,
              0.9220136,
              1.7535954
            ],
            [
              0.8662405,
              0.9184377,
              1.0065829,
              1.1551178,
              1.4196796,
              1.8986892,
              2.7721263
            ]
          ]
        },
        "related_pin": "A",
        "rise_transition,del_1_7_7": {
          "index_1": [
            0.01,
            0.0316228,
            0.1,
            0.316228,
            1,
            3.16228,
            10
          ],
          "index_2": [
            0.0044084,
            0.00538231,
            0.00825321,
            0.0167161,
            0.0416631,
            0.115202,
            0.331982
          ],
          "values": [
            [
              0.1265398,
              0.1572126,
              0.2457314,
              0.4961674,
              1.2508041,
              3.4559005,
              9.9734585
            ],
            [
              0.1262952,
              0.1564617,
              0.2416418,
              0.4978829,
              1.2477041,
              3.4552023,
              9.973979
            ],
            [
              0.1259561,
              0.1559873,
              0.2422521,
              0.5005431,
              1.2461825,
              3.4648975,
              9.9864597
            ],
            [
              0.1248596,
              0.154241,
              0.242898,
              0.5009253,
              1.2585617,
              3.4552268,
              9.9790052
            ],
            [
              0.1802951,
              0.194428,
              0.2635546,
              0.4983662,
              1.2473137,
              3.4623135,
              9.9677724
            ],
            [
              0.3915576,
              0.4269568,
              0.5196358,
              0.6994237,
              1.287448,
              3.4771024,
              9.9859943
            ],
            [
              1.0346027,
              1.1416497,
              1.2304145,
              1.5414785,
              2.1042224,
              3.71154,
              9.9891375
            ]
          ]
        },
        "timing_sense": "negative_unate",
        "timing_type": "combinational"
      },
      {
        "cell_fall,del_1_7_7": {
          "index_1": [
            0.01,
            0.0316228,
            0.1,
            0.316228,
            1,
            3.16228,
            10
          ],
          "index_2": [
            0.0044084,
            0.00538231,
            0.00825321,
            0.0167161,
            0.0416631,
            0.115202,
            0.331982
          ],
          "values": [
            [
              0.3567465,
              0.3633107,
              0.3805535,
              0.4232146,
              0.5301067,
              0.8207047,
              1.6710139
            ],
            [
              0.3673031,
              0.3740996,
              0.3912465,
              0.43402,
              0.5409165,
              0.8316192,
              1.6805833
            ],
            [
              0.4082638,
              0.4147919,
              0.4320993,
              0.4746959,
              0.5816045,
              0.8723379,
              1.7208317
            ],
            [
              0.5455808,
              0.5521378,
              0.5694199,
              0.6120091,
              0.7187866,
              1.0094043,
              1.858988
            ],
            [
              0.9932893,
              0.9998463,
              1.0171196,
              1.0597566,
              1.1665127,
              1.4570249,
              2.30744
            ],
            [
              2.3476801,
              2.3561484,
              2.3795381,
              2.4294291,
              2.5421787,
              2.8356646,
              3.6867267
            ],
            [
              5.9514429,
              5.9652625,
              6.0047727,
              6.0856862,
              6.2353518,
              6.5561516,
              7.4093642
            ]
          ]
        },
        "cell_rise,del_1_7_7": {
          "index_1": [
            0.01,
            0.0316228,
            0.1,
            0.316228,
            1,
            3.16228,
            10
          ],
          "index_2": [
            0.0044084,
            0.00538231,
            0.00825321,
            0.0167161,
            0.0416631,
            0.115202,
            0.331982
          ],
          "values": [
            [
              0.2083196,
              0.2310142,
              0.2986853,
              0.4976443,
              1.0839711,
              2.8135374,
              7.9100104
            ],
            [
              0.2214179,
              0.2441351,
              0.3117369,
              0.5106908,
              1.0969509,
              2.8315916,
              7.9200486
            ],
            [
              0.2670384,
              0.2897182,
              0.3574313,
              0.5564054,
              1.1423338,
              2.8858054,
              7.9744034
            ],
            [
              0.4118545,
              0.4346903,
              0.5029467,
              0.7019285,
              1.2871544,
              3.0215264,
              8.1209555
            ],
            [
              0.8625299,
              0.8859554,
              0.9539176,
              1.1527672,
              1.7389971,
              3.4833283,
              8.5565022
            ],
            [
              2.1188682,
              2.1588038,
              2.2637912,
              2.5140763,
              3.1116272,
              4.8481463,
              9.9518909
            ],
            [
              5.5430447,
              5.6378937,
              5.8731766,
              6.36701,
              7.3020741,
              9.1638572,
              14.2786467
            ]
          ]
        },
        "fall_transition,del_1_7_7": {
          "index_1": [
            0.01,
            0.0316228,
            0.1,
            0.316228,
            1,
            3.16228,
            10
          ],
          "index_2": [
            0.0044084,
            0.00538231,
            0.00825321,
            0.0167161,
            0.0416631,
            0.115202,
            0.331982
          ],
          "values": [
            [
              0.0395233,
              0.0451217,
              0.0606918,
              0.1030338,
              0.223102,
              0.5880331,
              1.6808037
            ],
            [
              0.0395176,
              0.0451323,
              0.0611544,
              0.1030975,
              0.2232032,
              0.5885726,
              1.6816335
            ],
            [
              0.0395107,
              0.0451178,
              0.0605821,
              0.1030916,
              0.2232135,
              0.5886741,
              1.6827686
            ],
            [
              0.0395278,
              0.0451203,
              0.0610298,
              0.1033008,
              0.2232856,
              0.5884316,
              1.6807727
            ],
            [
              0.0395105,
              0.0450893,
              0.0610213,
              0.10334,
              0.2229859,
              0.5877375,
              1.6801864
            ],
            [
              0.053446,
              0.059451,
              0.0742865,
              0.1162885,
              0.2297062,
              0.5912481,
              1.6743552
            ],
            [
              0.1070177,
              0.115081,
              0.135197,
              0.1787164,
              0.285709,
              0.6146925,
              1.6879811
            ]
          ]
        },
        "related_pin": "TE_B",
        "rise_transition,del_1_7_7": {
          "index_1": [
            0.01,
            0.0316228,
            0.1,
            0.316228,
            1,
            3.16228,
            10
          ],
          "index_2": [
            0.0044084,
            0.00538231,
            0.00825321,
            0.0167161,
            0.0416631,
            0.115202,
            0.331982
          ],
          "values": [
            [
              0.1257978,
              0.1555339,
              0.2426814,
              0.4985841,
              1.2494978,
              3.4639611,
              9.9793667
            ],
            [
              0.1264055,
              0.1555568,
              0.242333,
              0.4984229,
              1.2480449,
              3.4583298,
              10.0011013
            ],
            [
              0.1261324,
              0.1555718,
              0.2435826,
              0.4984551,
              1.2476308,
              3.4616356,
              9.9880477
            ],
            [
              0.1262765,
              0.1553438,
              0.2450835,
              0.4985479,
              1.2468171,
              3.45902,
              9.9715276
            ],
            [
              0.1339714,
              0.1615565,
              0.2445318,
              0.4982083,
              1.2488159,
              3.4659757,
              9.9937578
            ],
            [
              0.2270457,
              0.26216,
              0.3520385,
              0.5757694,
              1.2595524,
              3.4591916,
              9.9706963
            ],
            [
              0.544264,
              0.6080407,
              0.7550581,
              1.0572936,
              1.7089596,
              3.5644387,
              9.9788382
            ]
          ]
        },
        "timing_sense": "negative_unate",
        "timing_type": "three_state_enable"
      },
      {
        "cell_fall,del_1_7_7": {
          "index_1": [
            0.01,
            0.0316228,
            0.1,
            0.316228,
            1,
            3.16228,
            10
          ],
          "index_2": [
            0.0044084,
            0.00538231,
            0.00825321,
            0.0167161,
            0.0416631,
            0.115202,
            0.331982
          ],
          "values": [
            [
              0.0736651,
              0.0736651,
              0.0736651,
              0.0737447,
              0.0737447,
              0.0737447,
              0.0737447
            ],
            [
              0.0854191,
              0.0854191,
              0.0854191,
              0.0857714,
              0.0857714,
              0.0857714,
              0.0857714
            ],
            [
              0.1056688,
              0.1057628,
              0.1057628,
              0.1067226,
              0.1067226,
              0.1067226,
              0.1067226
            ],
            [
              0.0357027,
              0.0357515,
              0.0361347,
              0.0361347,
              0.0361347,
              0.0361347,
              0.037667
            ],
            [
              -0.32992,
              -0.3298244,
              -0.3298244,
              -0.3298244,
              -0.3298244,
              -0.329542,
              -0.3242962
            ],
            [
              -1.3503589,
              -1.3499368,
              -1.3480009,
              -1.3444086,
              -1.3444086,
              -1.3444086,
              -1.3317853
            ],
            [
              -4.657732,
              -4.657732,
              -4.657732,
              -4.6572746,
              -4.6572746,
              -4.6568518,
              -4.6568518
            ]
          ]
        },
        "cell_rise,del_1_7_7": {
          "index_1": [
            0.01,
            0.0316228,
            0.1,
            0.316228,
            1,
            3.16228,
            10
          ],
          "index_2": [
            0.0044084,
            0.00538231,
            0.00825321,
            0.0167161,
            0.0416631,
            0.115202,
            0.331982
          ],
          "values": [
            [
              0.0880159,
              0.0882008,
              0.0882008,
              0.0882008,
              0.0882142,
              0.0882142,
              0.0882169
            ],
            [
              0.1010708,
              0.1013055,
              0.1013055,
              0.1013055,
              0.1013055,
              0.1013055,
              0.1013055
            ],
            [
              0.1429615,
              0.1430745,
              0.1431911,
              0.1431911,
              0.1431911,
              0.1431911,
              0.1431911
            ],
            [
              0.2629967,
              0.2645899,
              0.2648039,
              0.2648039,
              0.2648039,
              0.2648039,
              0.2648039
            ],
            [
              0.5653818,
              0.5653818,
              0.5653818,
              0.5653818,
              0.5653818,
              0.5653818,
              0.5653818
            ],
            [
              1.3470135,
              1.3470135,
              1.3470135,
              1.347126,
              1.347126,
              1.347126,
              1.347126
            ],
            [
              3.2423977,
              3.2461278,
              3.2524849,
              3.2524849,
              3.2534215,
              3.2536187,
              3.2536187
            ]
          ]
        },
        "fall_transition,scalar": {
          "values": [
            0.0
          ]
        },
        "related_pin": "TE_B",
        "rise_transition,scalar": {
          "values": [
            0.0
          ]
        },
        "timing_sense": "positive_unate",
        "timing_type": "three_state_disable"
      }
    ]
  }
}